odoo/addons/sales_team_invoiced_target_domain/README.rst
odoo/addons/sales_team_invoiced_target_domain/__init__.py
odoo/addons/sales_team_invoiced_target_domain/__manifest__.py
odoo/addons/sales_team_invoiced_target_domain/i18n/it.po
odoo/addons/sales_team_invoiced_target_domain/i18n/sales_team_invoiced_target_domain.pot
odoo/addons/sales_team_invoiced_target_domain/model/__init__.py
odoo/addons/sales_team_invoiced_target_domain/model/crm_team.py
odoo/addons/sales_team_invoiced_target_domain/model/res_company.py
odoo/addons/sales_team_invoiced_target_domain/model/res_config_settings.py
odoo/addons/sales_team_invoiced_target_domain/readme/CONTRIBUTORS.md
odoo/addons/sales_team_invoiced_target_domain/readme/DESCRIPTION.md
odoo/addons/sales_team_invoiced_target_domain/readme/USAGE.md
odoo/addons/sales_team_invoiced_target_domain/static/description/icon.png
odoo/addons/sales_team_invoiced_target_domain/static/description/index.html
odoo/addons/sales_team_invoiced_target_domain/tests/__init__.py
odoo/addons/sales_team_invoiced_target_domain/tests/test_crm_team.py
odoo/addons/sales_team_invoiced_target_domain/views/res_config_settings_views.xml
odoo_addon_sales_team_invoiced_target_domain-17.0.1.0.0.4.dist-info/METADATA
odoo_addon_sales_team_invoiced_target_domain-17.0.1.0.0.4.dist-info/WHEEL
odoo_addon_sales_team_invoiced_target_domain-17.0.1.0.0.4.dist-info/top_level.txt
odoo_addon_sales_team_invoiced_target_domain-17.0.1.0.0.4.dist-info/RECORD
